WebsitesAvailability-1.1.0.data/scripts/recorder.py
WebsitesAvailability-1.1.0.data/scripts/tracker.py
libs/__init__.py
libs/log.py
libs/status.py
libs/webtracker.py
tests/__init__.py
tests/test_websitestatus.py
tests/test_webtracker.py
WebsitesAvailability-1.1.0.dist-info/LICENSE
WebsitesAvailability-1.1.0.dist-info/METADATA
WebsitesAvailability-1.1.0.dist-info/WHEEL
WebsitesAvailability-1.1.0.dist-info/top_level.txt
WebsitesAvailability-1.1.0.dist-info/RECORD
